my_own_package/__init__.py
alex_proiect_hello-0.2.0.dist-info/METADATA
alex_proiect_hello-0.2.0.dist-info/WHEEL
alex_proiect_hello-0.2.0.dist-info/top_level.txt
alex_proiect_hello-0.2.0.dist-info/RECORD
