Metadata-Version: 2.1
Name: alex-proiect-hello
Version: 0.2.0
Summary: says hello to owner
Home-page: UNKNOWN
Author: Alex T.
Author-email: alex.tudor@macromex.com
License: UNKNOWN
Platform: UNKNOWN
